6_stage_with data forwarding/Pipelined.v
module Pipelined(clk1,clk2);
	input clk1,clk2;				 // Two-phase clock
	reg[31:0]  PC,IF_ID_IR,IF_ID_NPC;
	reg[31:0]  ID_RR_IR,ID_RR_NPC,RR_EX_A,RR_EX_B,RR_EX_Imm,RR_EX_NPC,RR_EX_IR;
	reg[2:0]   ID_RR_type,EX_MEM_type,MEM_WB_type,RR_EX_type;
	reg[31:0]  EX_MEM_IR,EX_MEM_ALUOut,EX_MEM_B;
	reg 	   EX_MEM_cond;                             
	reg[31:0]  MEM_WB_IR,MEM_WB_ALUOut,MEM_WB_LMD;
	reg[31:0]  Reg[0:31];				// Register bank(32x32)
	reg[31:0]  Mem[0:1023];				// 1024x32 memory
	wire[31:0] RR_EX_A_OF, RR_EX_B_OF;
	wire bypassAfromMEM, bypassBfromMEM, bypassAfromWB, bypassBfromWB;
	
	reg HALTED;		    // Set after HLT instruction is completed(in WB stage)
	wire TAKEN_BRANCH;	// Required to disable instructions after branch
	
	parameter	ADD=6'b000000,SUB=6'b000001,AND=6'b000010,OR=6'b000011,SLT=6'b000100,MUL=6'b000101,
				HLT=6'b111111,LW=6'b001000,SW=6'b001001,ADDI=6'b001010,SUBI=6'b001011,SLTI=6'b001100,
				BNEQ=6'b001101,BEQ=6'b001110;
    
	parameter   RR_ALU=3'b000,RM_ALU=3'b001,LOAD=3'b010,STORE=3'b011,BRANCH=3'b100,HALT=3'b101;
	/////////////////////////////////Operend_Forwarding/////////////////////////////////////////////
	assign bypassAfromMEM = (RR_EX_IR[20:16] == EX_MEM_IR[25:21]) & (EX_MEM_IR[25:21] != 0);
	assign bypassBfromMEM = (RR_EX_IR[15:11] == EX_MEM_IR[25:21]) & (EX_MEM_IR[25:21] != 0);
	
	assign bypassAfromWB = (RR_EX_IR[20:16] == MEM_WB_IR[25:21]) & (MEM_WB_IR[25:21] != 0) & (EX_MEM_IR[25:21] != RR_EX_IR[20:16]);
	assign bypassBfromWB = (RR_EX_IR[15:11] == MEM_WB_IR[25:21]) & (MEM_WB_IR[25:21] != 0) & (EX_MEM_IR[25:21] != RR_EX_IR[15:11]);
	
	assign RR_EX_A_OF =  bypassAfromMEM ? EX_MEM_ALUOut : (bypassAfromWB) ? MEM_WB_ALUOut : RR_EX_A;
	assign RR_EX_B_OF =  bypassBfromMEM ? EX_MEM_ALUOut : (bypassBfromWB) ? MEM_WB_ALUOut : RR_EX_B;
	
	// Signal for a taken branch: instruction is BEQ and registers are equal
	assign TAKEN_BRANCH = (IF_ID_IR[31:26] == BEQ) && (Reg[IF_ID_IR[20:16]] == Reg[IF_ID_IR[15:11]]) || 
						  (IF_ID_IR[31:26] == BNEQ) && (Reg[IF_ID_IR[20:16]] != Reg[IF_ID_IR[15:11]]);
	
	/* // The signal for detecting a stall based on the use of a result from LW
	 assign stall = (MEMWBIR[31:26]==LW) && // source instruction is a load
	 ((((IDEXop==LW)|(IDEXop==SW)) && (IDEXrs==MEMWBrd)) | // stall for address calc
	((IDEXop==ALUop) && ((IDEXrs==MEMWBrd)|(IDEXrt==MEMWBrd)))); // ALU use */
	
	
	
	reg [5:0] i; //used to initialize registers 
/* 	initial begin 
		PC = 0; 
		IFIDIR=no-op; 
		IDEXIR=no-op; 
		EXMEMIR=no-op; 
		MEMWBIR=no-op; // put no-ops in pipeline registers
		for (i=0;i<=31;i=i+1) 
		Regs[i] = i; //initialize registers--just so they aren’t don’t cares
	 end */
////////////////////////////////////////////////////////IF Stage////////////////////////////////////////////////////////
	always @(posedge clk1)													
		if((~HALTED))
			begin
				if(((EX_MEM_IR[31:26]== BEQ)&&(EX_MEM_cond ==1)) || ((EX_MEM_IR[31:26]== BNEQ)&&(EX_MEM_cond==0)))
					begin
					   IF_ID_IR	    	<=  Mem[EX_MEM_ALUOut];
					   //TAKEN_BRANCH		<=  1'b1;
					   IF_ID_NPC    	<=  EX_MEM_ALUOut + 1;
					   PC				<=  EX_MEM_ALUOut + 1;
					end
				else
					begin
						IF_ID_IR		<= Mem[PC];
						IF_ID_NPC		<= PC+1;
						PC				<= PC+1;
					end
			end
////////////////////////////////////////////////////////ID Stage////////////////////////////////////////////////////////
	always@(posedge clk2)
		if((~HALTED))
			begin
				ID_RR_NPC		<=  IF_ID_NPC;
				ID_RR_IR		<=  IF_ID_IR;
				
				case(IF_ID_IR[31:26])
					ADD,SUB,AND,OR,SLT,MUL:   	ID_RR_type <=  RR_ALU;
					ADDI,SUBI,SLTI:		    	ID_RR_type <=  RM_ALU;
					LW:							ID_RR_type <=  LOAD;
					SW:							ID_RR_type <=  STORE; 
					BNEQ,BEQ:					ID_RR_type <=  BRANCH;
					HLT:						ID_RR_type <=  HALT;
					default:					ID_RR_type <=  HALT;
				endcase
			end
////////////////////////////////////////////////////////RR Stage////////////////////////////////////////////////////////
	always@(posedge clk1)
		if((~HALTED))
			begin
				if(ID_RR_IR[20:16]==5'b00000)	// If R0 is accessed which is always 0
					RR_EX_A	<= 0;
				else 
					RR_EX_A	<=  Reg[ID_RR_IR[20:16]];		// "rs"
                               
				if(ID_RR_IR[15:11]== 5'b00000)	// If R0 is accessed which is always 0
					RR_EX_B	<=0;
				else 
					RR_EX_B	<=  Reg[ID_RR_IR[15:11]];		// "rt"
				
				RR_EX_type      <=  ID_RR_type;
				RR_EX_NPC		<=  ID_RR_NPC;
				RR_EX_IR		<=  ID_RR_IR;
				RR_EX_Imm		<=  {{16{ID_RR_IR[15]}},{ID_RR_IR[15:0]}}; // Immediate type data is sign extended to 32 (I-type) 
			end
			
////////////////////////////////////////////////////////EX Stage////////////////////////////////////////////////////////
	always@(posedge clk2)
		if((~HALTED))
			begin
				EX_MEM_type		<=  RR_EX_type;
				EX_MEM_IR		<=  RR_EX_IR;
				//TAKEN_BRANCH	<=  1'b0;
				////////////////////////////////////////////////////////////////

					
				case(ID_RR_type)
					RR_ALU:	begin
						case(RR_EX_IR[31:26])	//"opcode"                                                        -
							ADD:	EX_MEM_ALUOut	<=  RR_EX_A_OF + RR_EX_B_OF;
							SUB:	EX_MEM_ALUOut	<=  RR_EX_A_OF - RR_EX_B_OF;
							AND:	EX_MEM_ALUOut	<=  RR_EX_A_OF & RR_EX_B_OF;
							OR:     EX_MEM_ALUOut	<=  RR_EX_A_OF | RR_EX_B_OF;
							SLT:    EX_MEM_ALUOut	<=  RR_EX_A_OF < RR_EX_B_OF;
							MUL:    EX_MEM_ALUOut	<=  RR_EX_A_OF * RR_EX_B_OF;
							default:EX_MEM_ALUOut	<=  32'hxxxxxxxx;
						endcase
					end
			
					RM_ALU:	begin
						case(RR_EX_IR[31:26])	//"opcode"
							ADDI:		EX_MEM_ALUOut	<=  RR_EX_A + RR_EX_Imm;
							SUBI:		EX_MEM_ALUOut	<=  RR_EX_A - RR_EX_Imm;
							SLTI:		EX_MEM_ALUOut	<=  RR_EX_A < RR_EX_Imm;
							default:	EX_MEM_ALUOut   <=  32'hxxxxxxxx;
						endcase
					end							  
					
					LOAD,STORE:	begin
						EX_MEM_ALUOut 	<= RR_EX_A + RR_EX_Imm;
						EX_MEM_B 		<= RR_EX_B;
					end
					BRANCH:	begin
						EX_MEM_ALUOut 	<= RR_EX_NPC + RR_EX_Imm;
						EX_MEM_cond 	<= (RR_EX_A == 0);
					end
				endcase
			end
////////////////////////////////////////////////////////MEM Stage////////////////////////////////////////////////////////			
	always@(posedge clk1)
		if((~HALTED))
			begin
				MEM_WB_type	<=  EX_MEM_type;
				MEM_WB_IR	<=  EX_MEM_IR;
				case(EX_MEM_type)
					RR_ALU,RM_ALU:	MEM_WB_ALUOut 		<= EX_MEM_ALUOut;
					LOAD:			MEM_WB_LMD			<= Mem[EX_MEM_ALUOut];
					STORE:			if(TAKEN_BRANCH ==0)						// Disable write
										Mem[EX_MEM_ALUOut]	<= EX_MEM_B;
				endcase
			end
    
////////////////////////////////////////////////////////WB Stage////////////////////////////////////////////////////////
	always@(posedge clk2)
		begin
			if(TAKEN_BRANCH == 0)		// Disable write if branch taken
			case(MEM_WB_type)
				RR_ALU:		Reg[MEM_WB_IR[25:21]] <=  MEM_WB_ALUOut;		//"rd"
				RM_ALU:		Reg[MEM_WB_IR[25:21]] <=  MEM_WB_ALUOut;		//"rt"
				LOAD:		Reg[MEM_WB_IR[25:21]] <=  MEM_WB_LMD;			//"rt"
				HALT:		HALTED 				  <=  1'b1;
			endcase
		end
       
endmodule

6_stage_with data forwarding/Pipelined_t.v
module test_mips32;
	reg clk1,clk2;
	integer k;
	Pipelined mips(clk1,clk2);
	  initial
		begin
			clk1=0;
			repeat(60)				// Generating 2-Phase Clock
				begin
					#10 clk1=1; #10 clk1=0;
					#5 clk2=1; #5 clk2=0;
				end
		end

	initial
		begin
			for(k=0;k<31;k=k+1)
				mips.Reg[k]=k;
     
			mips.Mem[0] = 32'h2820000a; 	// ADDI R1,RO,10
			mips.Mem[1] = 32'h28400014;		// ADDI R2,RO,20
			mips.Mem[2] = 32'h28600019;		// ADDI R3,RO,25
			mips.Mem[3] = 32'h0ce77800;     // OR R7,R7,R7 -- dummy instr.         
			mips.Mem[4] = 32'h0ce77800;		// OR R7,R7,R7 -- dummy instr. 
			mips.Mem[5] = 32'h00811000;		// ADD R4,R1,R2
			//mips.Mem[6] = 32'h0ce77800;		// OR R7,R7,R7 -- dummy instr. 
			mips.Mem[6] = 32'h00c21800;		// ADD R6,R2,R3
			//mips.Mem[7] = 32'h00e11800;		// ADD R7,R1,R3
			mips.Mem[7] = 32'h00a41800;		// ADD R5,R4,R3
			mips.Mem[8] = 32'hfc000000;		// HLT

			mips.HALTED = 0;
			mips.PC = 0;
			force mips.TAKEN_BRANCH = 0;
			
			#300
			for(k=0;k<7;k=k+1)
			  $display("R%1d - %d",k,mips.Reg[k]);
		end
	initial
		begin
			$dumpfile ("mips.vcd");
			$dumpvars (0,test_mips32);
			#300 $finish;
		end
endmodule

6_stage_with data forwarding/mips.vcd
$date
	Sat Apr 13 00:41:37 2024
$end
$version
	Icarus Verilog
$end
$timescale
	1s
$end
$scope module test_mips32 $end
$var reg 1 ! clk1 $end
$var reg 1 " clk2 $end
$var integer 32 # k [31:0] $end
$scope module mips $end
$var wire 1 $ TAKEN_BRANCH $end
$var wire 1 % bypassAfromMEM $end
$var wire 1 & bypassAfromWB $end
$var wire 1 ' bypassBfromMEM $end
$var wire 1 ( bypassBfromWB $end
$var wire 1 ! clk1 $end
$var wire 1 " clk2 $end
$var wire 32 ) RR_EX_B_OF [31:0] $end
$var wire 32 * RR_EX_A_OF [31:0] $end
$var reg 32 + EX_MEM_ALUOut [31:0] $end
$var reg 32 , EX_MEM_B [31:0] $end
$var reg 32 - EX_MEM_IR [31:0] $end
$var reg 1 . EX_MEM_cond $end
$var reg 3 / EX_MEM_type [2:0] $end
$var reg 1 0 HALTED $end
$var reg 32 1 ID_RR_IR [31:0] $end
$var reg 32 2 ID_RR_NPC [31:0] $end
$var reg 3 3 ID_RR_type [2:0] $end
$var reg 32 4 IF_ID_IR [31:0] $end
$var reg 32 5 IF_ID_NPC [31:0] $end
$var reg 32 6 MEM_WB_ALUOut [31:0] $end
$var reg 32 7 MEM_WB_IR [31:0] $end
$var reg 32 8 MEM_WB_LMD [31:0] $end
$var reg 3 9 MEM_WB_type [2:0] $end
$var reg 32 : PC [31:0] $end
$var reg 32 ; RR_EX_A [31:0] $end
$var reg 32 < RR_EX_B [31:0] $end
$var reg 32 = RR_EX_IR [31:0] $end
$var reg 32 > RR_EX_Imm [31:0] $end
$var reg 32 ? RR_EX_NPC [31:0] $end
$var reg 3 @ RR_EX_type [2:0] $end
$upscope $end
$upscope $end
$enddefinitions $end
#0
$dumpvars
bx @
bx ?
bx >
bx =
bx <
bx ;
b0 :
bx 9
bx 8
bx 7
bx 6
bx 5
bx 4
bx 3
bx 2
bx 1
00
bx /
x.
bx -
bx ,
bx +
bx *
bx )
x(
x'
x&
x%
0$
b11111 #
x"
0!
$end
#10
0$
b1 :
b1 5
b101000001000000000000000001010 4
1!
#20
0!
#25
b1 3
b101000001000000000000000001010 1
b1 2
1"
#30
0"
#40
b1010 >
b101000001000000000000000001010 =
b1 ?
b1 @
b0 <
b0 ;
b10 :
b10 5
b101000010000000000000000010100 4
1!
#50
0!
#55
0%
0'
b1010 +
b101000001000000000000000001010 -
b1 /
b101000010000000000000000010100 1
b10 2
1"
#60
0"
#70
0&
0(
b0 *
b0 )
b11 :
b11 5
b101000011000000000000000011001 4
b10100 >
b101000010000000000000000010100 =
b10 ?
b1010 6
b101000001000000000000000001010 7
b1 9
1!
#80
0!
#85
b101000011000000000000000011001 1
b11 2
b10100 +
b101000010000000000000000010100 -
1"
#90
0"
#100
b10100 6
b101000010000000000000000010100 7
b11001 >
b101000011000000000000000011001 =
b11 ?
b100 :
b100 5
b1100111001110111100000000000 4
1!
#110
0!
#115
b11001 +
b101000011000000000000000011001 -
b0 3
b1100111001110111100000000000 1
b100 2
1"
#120
0"
#130
b1111 )
b111 *
b101 :
b101 5
b111100000000000 >
b1100111001110111100000000000 =
b100 ?
b0 @
b1111 <
b111 ;
b11001 6
b101000011000000000000000011001 7
1!
#140
0!
#145
b1111 *
1%
b101 2
b1111 +
b1100111001110111100000000000 -
b0 /
1"
#150
0"
#160
b1111 6
b1100111001110111100000000000 7
b0 9
b101 ?
b110 :
b110 5
b100000010001000000000000 4
1!
#170
0!
#175
b100000010001000000000000 1
b110 2
1"
#180
0"
#190
b1010 *
0%
0&
b10100 )
b111 :
b111 5
b110000100001100000000000 4
b1000000000000 >
b100000010001000000000000 =
b110 ?
b10100 <
b1010 ;
1!
#200
0!
#205
b110000100001100000000000 1
b111 2
b11110 +
b100000010001000000000000 -
1"
#210
0"
#220
b11001 )
b10100 *
b11110 6
b100000010001000000000000 7
b1100000000000 >
b110000100001100000000000 =
b111 ?
b11001 <
b10100 ;
b1000 :
b1000 5
b101001000001100000000000 4
1!
#230
0!
#235
b101101 +
b110000100001100000000000 -
b101001000001100000000000 1
b1000 2
1"
#240
0"
#250
b11110 *
b1001 :
b1001 5
b11111100000000000000000000000000 4
b101001000001100000000000 =
b1000 ?
b11110 ;
b101101 6
b110000100001100000000000 7
1!
#260
0!
#265
b101 3
b11111100000000000000000000000000 1
b1001 2
b110111 +
b101001000001100000000000 -
1"
#270
0"
#280
b0 )
b0 *
b110111 6
b101001000001100000000000 7
b0 >
b11111100000000000000000000000000 =
b1001 ?
b101 @
b0 <
b0 ;
b1010 :
b1010 5
bx 4
1!
#290
0!
#295
b11111100000000000000000000000000 -
b101 /
bx 1
b1010 2
1"
#300
0"
b111 #
